mcp_server_glm_vision/__init__.py
mcp_server_glm_vision-1.0.1.dist-info/METADATA
mcp_server_glm_vision-1.0.1.dist-info/WHEEL
mcp_server_glm_vision-1.0.1.dist-info/licenses/LICENSE
mcp_server_glm_vision-1.0.1.dist-info/RECORD
