Metadata-Version: 2.4
Name: mcp-server-glm-vision
Version: 1.0.1
Summary: MCP Server for GLM-4.5V integration with Claude Code
Author-email: Danilo Falcão <danilo@falcao.org>
License: MIT
License-File: LICENSE
Requires-Python: >=3.10
Requires-Dist: httpx>=0.25.0
Requires-Dist: mcp>=1.0.0
Provides-Extra: dev
Requires-Dist: black>=23.0.0; extra == 'dev'
Requires-Dist: isort>=5.12.0; extra == 'dev'
Requires-Dist: mypy>=1.5.0; extra == 'dev'
Requires-Dist: pytest-asyncio>=0.21.0; extra == 'dev'
Requires-Dist: pytest>=7.0.0; extra == 'dev'
